pyjak/__init__.py
pyjak/convert.py
pyjak/order.py
pyjak-0.1.1.dist-info/LICENSE
pyjak-0.1.1.dist-info/METADATA
pyjak-0.1.1.dist-info/WHEEL
pyjak-0.1.1.dist-info/top_level.txt
pyjak-0.1.1.dist-info/RECORD
