Metadata-Version: 2.1
Name: pyjak
Version: 0.1.1
Summary: A Python library for reading and writing binary sources.
Home-page: https://github.com/miniwa/pyjak
Author: Max Byrde
Author-email: max.byrde@gmail.com
License: MIT
Platform: UNKNOWN
Classifier: Programming Language :: Python :: 3
Classifier: Programming Language :: Python :: 3.4
Classifier: Programming Language :: Python :: 3.5
Classifier: Programming Language :: Python :: 3.6
Classifier: Programming Language :: Python :: 3.7
Classifier: License :: OSI Approved :: MIT License
Classifier: Operating System :: OS Independent
Classifier: Intended Audience :: Developers
